eurepoc/__init__.py
eurepoc/data_cleaning_utils.py
eurepoc/data_query_utils.py
eurepoc/database_query.py
eurepoc/incident_dataframes.py
eurepoc/read_token.py
eurepoc/table_models.py
eurepoc/tables.py
eurepoc-0.1.9.dist-info/LICENSE
eurepoc-0.1.9.dist-info/METADATA
eurepoc-0.1.9.dist-info/WHEEL
eurepoc-0.1.9.dist-info/top_level.txt
eurepoc-0.1.9.dist-info/RECORD
