Metadata-Version: 2.1
Name: eurepoc
Version: 0.1.9
Summary: Wrapper for the EuRepoC API
Author: Camille Borrett
License: MIT
Project-URL: Documentation, https://eurepoc.readthedocs.io/
Project-URL: Source, https://github.com/camilleborrett/eurepoc
Project-URL: Tracker, https://github.com/camilleborrett/eurepoc/issues
Project-URL: EuRepoC Project, https://eurepoc.eu/
Requires-Python: >=3.6
License-File: LICENSE
Requires-Dist: requests <3.0.0,>=2.31.0
Requires-Dist: nested-query-string <0.1.0,>=0.0.1
Requires-Dist: pandas <3.0.0,>=2.2.2
Requires-Dist: pydantic <3.0.0,>=2.7.1
